{"otherData": {},"traceEvents":[{"cat":"function","dur":125622,"name":"glfwInit","ph":"X","pid":0,"tid":197146501,"ts":76806188940},{"cat":"function","dur":370628,"name":"glfwCreateWindow","ph":"X","pid":0,"tid":197146501,"ts":76806314752},{"cat":"function","dur":1426,"name":"void __cdecl Fraples::OpenGLContext::Init(void)","ph":"X","pid":0,"tid":197146501,"ts":76806685506},{"cat":"function","dur":9,"name":"void __cdecl Fraples::WindowsWindow::SetVSync(bool)","ph":"X","pid":0,"tid":197146501,"ts":76806687003},{"cat":"function","dur":498967,"name":"void __cdecl Fraples::WindowsWindow::Init(const struct Fraples::WindowProperties &)","ph":"X","pid":0,"tid":197146501,"ts":76806188110},{"cat":"function","dur":499020,"name":"__cdecl Fraples::WindowsWindow::WindowsWindow(const struct Fraples::WindowProperties &)","ph":"X","pid":0,"tid":197146501,"ts":76806188109},{"cat":"function","dur":5,"name":"void __cdecl Fraples::OpenGLRendererAPI::Init(void)","ph":"X","pid":0,"tid":197146501,"ts":76806687200},{"cat":"function","dur":23,"name":"__cdecl Fraples::OpenGLVertexArray::OpenGLVertexArray(void)","ph":"X","pid":0,"tid":197146501,"ts":76806687271},{"cat":"function","dur":292,"name":"__cdecl Fraples::OpenGLVertexBuffer::OpenGLVertexBuffer(float *,unsigned int)","ph":"X","pid":0,"tid":197146501,"ts":76806687362},{"cat":"function","dur":1,"name":"void __cdecl Fraples::OpenGLVertexBuffer::Bind(void) const","ph":"X","pid":0,"tid":197146501,"ts":76806687768},{"cat":"function","dur":85,"name":"void __cdecl Fraples::OpenGLVertexArray::AddVertexBuffer(const class std::shared_ptr<class Fraples::VertexBuffer> &)","ph":"X","pid":0,"tid":197146501,"ts":76806687759},{"cat":"function","dur":4,"name":"__cdecl Fraples::OpenGLIndexBuffer::OpenGLIndexBuffer(unsigned int *,unsigned int)","ph":"X","pid":0,"tid":197146501,"ts":76806687896},{"cat":"function","dur":1,"name":"void __cdecl Fraples::OpenGLIndexBuffer::Bind(void) const","ph":"X","pid":0,"tid":197146501,"ts":76806687960},{"cat":"function","dur":61,"name":"void __cdecl Fraples::OpenGLVertexArray::SetIndexBuffer(const class std::shared_ptr<class Fraples::IndexBuffer> &)","ph":"X","pid":0,"tid":197146501,"ts":76806687959},{"cat":"function","dur":134,"name":"__cdecl Fraples::OpenGLTexture2D::OpenGLTexture2D(unsigned int,unsigned int)","ph":"X","pid":0,"tid":197146501,"ts":76806688075},{"cat":"function","dur":395,"name":"void __cdecl Fraples::OpenGLTexture2D::SetData(void *,unsigned int)","ph":"X","pid":0,"tid":197146501,"ts":76806688280},{"cat":"function","dur":4080,"name":"class std::basic_string<char,struct std::char_traits<char>,class std::allocator<char> > __cdecl Fraples::OpenGLShader::ReadFile(const class std::basic_string<char,struct std::char_traits<char>,class std::allocator<char> > &)","ph":"X","pid":0,"tid":197146501,"ts":76806688751},{"cat":"function","dur":60,"name":"class std::unordered_map<unsigned int,class std::basic_string<char,struct std::char_traits<char>,class std::allocator<char> >,struct std::hash<unsigned int>,struct std::equal_to<unsigned int>,class std::allocator<struct std::pair<unsigned int const ,class std::basic_string<char,struct std::char_traits<char>,class std::allocator<char> > > > > __cdecl Fraples::OpenGLShader::PreProcess(const class std::basic_string<char,struct std::char_traits<char>,class std::allocator<char> > &)","ph":"X","pid":0,"tid":197146501,"ts":76806692922},{"cat":"function","dur":603,"name":"void __cdecl Fraples::OpenGLShader::Compile(const class std::unordered_map<unsigned int,class std::basic_string<char,struct std::char_traits<char>,class std::allocator<char> >,struct std::hash<unsigned int>,struct std::equal_to<unsigned int>,class std::allocator<struct std::pair<unsigned int const ,class std::basic_string<char,struct std::char_traits<char>,class std::allocator<char> > > > > &)","ph":"X","pid":0,"tid":197146501,"ts":76806693038},{"cat":"function","dur":4999,"name":"__cdecl Fraples::OpenGLShader::OpenGLShader(const class std::basic_string<char,struct std::char_traits<char>,class std::allocator<char> > &)","ph":"X","pid":0,"tid":197146501,"ts":76806688749},{"cat":"function","dur":5,"name":"void __cdecl Fraples::OpenGLShader::Bind(void) const","ph":"X","pid":0,"tid":197146501,"ts":76806693850},{"cat":"function","dur":7,"name":"void __cdecl Fraples::OpenGLShader::SetUniformInt(const class std::basic_string<char,struct std::char_traits<char>,class std::allocator<char> > &,int)","ph":"X","pid":0,"tid":197146501,"ts":76806693909},{"cat":"function","dur":6708,"name":"void __cdecl Fraples::Renderer2D::Init(void)","ph":"X","pid":0,"tid":197146501,"ts":76806687260},{"cat":"function","dur":6827,"name":"void __cdecl Fraples::Renderer::Init(void)","ph":"X","pid":0,"tid":197146501,"ts":76806687198},{"cat":"function","dur":147,"name":"void __cdecl Fraples::ImGuiLayer::OnAttach(void)","ph":"X","pid":0,"tid":197146501,"ts":76806694089},{"cat":"function","dur":207,"name":"void __cdecl Fraples::Application::PushOverLay(class Fraples::Layer *)","ph":"X","pid":0,"tid":197146501,"ts":76806694084},{"cat":"function","dur":506245,"name":"__cdecl Fraples::Application::Application(void)","ph":"X","pid":0,"tid":197146501,"ts":76806188095},{"cat":"function","dur":7,"name":"__cdecl Fraples::OrthographicCamera::OrthographicCamera(float,float,float,float)","ph":"X","pid":0,"tid":197146501,"ts":76806694400},{"cat":"function","dur":499828,"name":"stbi_load - OpenGLTexture2D::OpenGLTexture2D(const std::string&) stbi_load","ph":"X","pid":0,"tid":197146501,"ts":76806694475},{"cat":"function","dur":502073,"name":"__cdecl Fraples::OpenGLTexture2D::OpenGLTexture2D(const class std::basic_string<char,struct std::char_traits<char>,class std::allocator<char> > &)","ph":"X","pid":0,"tid":197146501,"ts":76806694473},{"cat":"function","dur":502149,"name":"void __cdecl SandBox2D::OnAttach(void)","ph":"X","pid":0,"tid":197146501,"ts":76806694468},{"cat":"function","dur":502206,"name":"void __cdecl Fraples::Application::PushLayer(class Fraples::Layer *)","ph":"X","pid":0,"tid":197146501,"ts":76806694462}]}